<resources>

    <string name="settings_curriculum">CurriculumSettings</string>
    <!-- The prompt for failed causes -->
    <string name="fail_cause_same_course_name">Same course name!</string>
    <string name="fail_cause_course_name_not_exist">The course does NOT exist!</string>
    <string name="fail_cause_unknown">Unknown</string>
    <!-- 本学期第x周星期y -->
    <string name="week_format_semester">W%1$s %2$s</string>
    <string name="arrow_left">←</string>
    <string name="arrow_right">→</string>
    <string name="prompt_fill_curriculum">Please fill curriculum!</string>
    <string name="prompt_demo_fill_curriculum">A demo below! Please fill curriculum!</string>
    <string name="show_courses_in_public_holidays">Show Courses in Public Holidays</string>
    <string name="prompt_set_curriculum_label">Curriculum may have a label!</string>
    <string name="hint_curriculum_label">Free text as label, info like class and/or grade etc.</string>
    <string name="set_semester_start_date">SemesterStartDate</string>
    <string name="set_semester_end_date">SemesterEndDate</string>
    <string name="format_semester_start">Semester Start %s</string>
    <string name="format_semester_end">Semester End  %s</string>
    <string name="morning_reading">早读</string>
    <string name="evening_study">晚自习</string>
    <string name="time_off_school">TimeOffSchool</string>
    <string name="set_time_off_school">SetTimeOffSchool</string>
    <string name="clear_time_off_school">ClearTimeOffSchool</string>
    <string name="set_time_off_school_time">Set Time</string>
    <string name="set_time_off_school_colors">Set Colors</string>
    <string name="set_curriculum_label">Set Curriculum Label</string>
    <string name="edit_curriculum_label">Edit Curriculum Label</string>
    <string name="set_course">Set</string>
    <string name="morning_course_1">AM 1</string>
    <string name="morning_course_2">AM 2</string>
    <string name="morning_course_3">AM 3</string>
    <string name="morning_course_4">AM 4</string>
    <string name="afternoon_course_1">PM 1</string>
    <string name="afternoon_course_2">PM 2</string>
    <string name="afternoon_course_3">PM 3</string>
    <string name="afternoon_course_4">PM 4</string>
    <string name="class_time">ClassTime</string>
    <string name="class_time_start">ClassTimeStart</string>
    <string name="class_time_end">ClassTimeEnd</string>
    <string name="show_class_time_in_widget">ShowInWidget</string>
    <string name="not_show_class_time_in_widget">NoShowInWidget</string>
    <string name="set_course_by_date">Set Courses on Date</string>
    <string name="color_scheme">Curriculum Color Scheme</string>
    <string name="color_set_same">Courses in same color</string>
    <string name="color_set_course_different">Courses in different colors</string>
    <string name="change_colors">ChangeColors</string>
    <string name="curriculum_add">NewCurriculum</string>
    <string name="prompt_add_curriculum">Are you sure to add a new curriculum?</string>
    <string name="curriculum_del">DelCurriculum</string>
    <string name="prompt_delete_curriculum">Are you sure to delete the current curriculum?</string>
    <string name="failed_add_course">Failed to add course: %1$s!\n%2$s</string>
    <string name="failed_delete_course">Failed to delete the course: %1$s!\n%2$s</string>
    <string name="text_course">Course</string>
    <string name="text_location">Location</string>
    <string name="select_course">Select a Course</string>
    <string name="add_course">Add a Course</string>
    <string name="clear_course">Clear</string>
    <string name="morning_no_course">FreeReading</string>
    <string name="morning_with_course">CourseReading</string>
    <string name="add_morning_reading_course">AddMorningCourse</string>
    <string name="evening_no_course">FreeStudy</string>
    <string name="evening_with_course">CourseStudy</string>
    <string name="add_evening_study_course">AddEveningCourse</string>
    <string name="curriculum_reset">Reset</string>
    <string name="curriculum_restore_default">RestoreDefaultCourses</string>
    <string name="curriculum_import">Import</string>
    <string name="curriculum_export">Export</string>
    <string name="confirm_restore_default_courses">Restoring to default courses will clear the current curriculum!\nAre you sure to do the action?</string>
    <string name="course_name">CourseName</string>
    <string name="course_teacher">CourseTeacher</string>
    <string name="course_teacher_visible">TeacherVisible</string>
    <string name="course_location">CourseLocation</string>
    <string name="course_location_visible">LocationVisible</string>
    <string name="course_colors">CourseColors</string>
    <string name="delete_course">Delete</string>
    <string name="edit_course">Edit</string>
    <string name="course_type">CourseType</string>
    <string name="course_type_major">Major</string>
    <string name="course_type_minor">Minor</string>
    <string name="course_type_art">Art</string>
    <string name="course_type_self">Self</string>
    <string name="course_type_fun">Fun</string>
    <string name="course_type_other">Other</string>
    <string name="course_type_reading">Reading</string>
    <string name="prompt_select_courses_below">Please select a course from below.</string>
    <string name="hint_input_course_name">Please enter course name here!</string>
    <string name="add_date">Add Date</string>
    <string name="clear_dates">Clear</string>
    <string name="remove_date">Delete</string>
    <string name="edit_date">Edit</string>
    <string name="take_weekday_courses">Take %s courses.</string>
    <string name="title_date_overwrite">Confirm overwritting date with courses</string>
    <string name="prompt_date_overwrite">The date has existed. Are you sure to overwrite the existing date?</string>
    <string name="title_delete_date_courses">Delete date courses</string>
    <string name="prompt_clear_dates_courses">Are you sure to clear all date courses setting?</string>
    <string name="prompt_delete_date_courses">Are you sure to delete the courses setting for %1$s?</string>
    <string name="prompt_delete_course">Are you sure to delete the course [%1$s]?</string>
    <string name="info_no_course_set">No Course</string>
    <string name="info_course_count">%d courses</string>
    <string name="no_morning_reading">NoReading</string>
    <string name="no_evening_study">NoStudy</string>
    <string name="format_course_count_in_a_week">%d a week</string>
    <string name="confirm_clear_course">Are you sure to clear course?\n%s</string>
    <string name="confirm_clear_time_off_school">Are you sure to clear the time off school for %s?</string>
    <string name="confirm_clear_curriculum">Are you sure to clear the current curriculum?</string>
    <string name="date_courses_same_as_weekday">Same courses as a week day</string>
    <string name="date_courses_specify">Specify date courses</string>
    <string name="prompt_no_date_set">No date set!</string>
    <string name="prompt_no_date_courses_set">No date with courses!</string>
    <string name="format_n_date_courses_set">%d dates with courses.</string>
    <string name="subject_chinese">语文</string>
    <string name="subject_math">数学</string>
    <string name="subject_english">英语</string>
    <string name="subject_politics">政治</string>
    <string name="subject_history">历史</string>
    <string name="subject_geography">地理</string>
    <string name="subject_phycics">物理</string>
    <string name="subject_chemistry">化学</string>
    <string name="subject_biology">生物</string>
    <string name="subject_music">音乐</string>
    <string name="subject_art">美术</string>
    <string name="subject_pe">体育</string>
    <string name="subject_class">班会</string>
    <string name="subject_self">自习</string>
    <string name="subject_computer">计算机</string>
    <string name="subject_out">课外</string>

</resources>